setup.py
fmtest_distributions/Binomialdistribution.py
fmtest_distributions/Gaussiandistribution.py
fmtest_distributions/Generaldistribution.py
fmtest_distributions/__init__.py
fmtest_distributions.egg-info/PKG-INFO
fmtest_distributions.egg-info/SOURCES.txt
fmtest_distributions.egg-info/dependency_links.txt
fmtest_distributions.egg-info/not-zip-safe
fmtest_distributions.egg-info/top_level.txt