Metadata-Version: 1.0
Name: fmtest-distributions
Version: 0.1
Summary: Gaussian distributions
Home-page: UNKNOWN
Author: Felix Mak
Author-email: fhw.mak@gmail.com
License: UNKNOWN
Platform: UNKNOWN
